setup.py
yieldfrom/__init__.py
yieldfrom.http.client.egg-info/PKG-INFO
yieldfrom.http.client.egg-info/SOURCES.txt
yieldfrom.http.client.egg-info/dependency_links.txt
yieldfrom.http.client.egg-info/namespace_packages.txt
yieldfrom.http.client.egg-info/not-zip-safe
yieldfrom.http.client.egg-info/requires.txt
yieldfrom.http.client.egg-info/top_level.txt
yieldfrom/http/__init__.py
yieldfrom/http/client.py