Metadata-Version: 1.0
Name: yieldfrom.http.client
Version: 0.1.3
Summary: asyncio version of http.client
Home-page: http://github.com/rdbhost/
Author: David Keeney
Author-email: dkeeney@rdbhost.com
License: Python Software Foundation License
Keywords: asyncio,http,http.client
Platform: UNKNOWN
